addition_subtraction/__init__.py
addition_subtraction/add_sub.py
addition_subtraction-0.1.1.dist-info/LICENSE
addition_subtraction-0.1.1.dist-info/METADATA
addition_subtraction-0.1.1.dist-info/WHEEL
addition_subtraction-0.1.1.dist-info/RECORD
