Metadata-Version: 2.1
Name: addition-subtraction
Version: 0.1.1
Summary: With the `AddSub` class, you can switch between addition and subtraction operations dynamically, providing flexibility for various scenarios requiring different operations.
Home-page: https://github.com/colddsam/Addition-Subtraction-Package.git
License: MIT
Author: colddsam
Author-email: dassamratkumar772@gmail.com
Requires-Python: >=3.10,<4.0
Classifier: License :: OSI Approved :: MIT License
Classifier: Programming Language :: Python :: 3
Classifier: Programming Language :: Python :: 3.10
Classifier: Programming Language :: Python :: 3.11
Classifier: Programming Language :: Python :: 3.12
Project-URL: Repository, https://github.com/colddsam/Addition-Subtraction-Package.git
